vecclean/__init__.py
vecclean/version.py
vecclean/api/deps.py
vecclean/api/main.py
vecclean/api/schemas.py
vecclean/chunk/splitter.py
vecclean/clean/normalize.py
vecclean/cli/__main__.py
vecclean/core/config.py
vecclean/core/embedding.py
vecclean/core/pipeline.py
vecclean/core/types.py
vecclean/cpp/include/cleaner.hpp
vecclean/cpp/src/bindings.cpp
vecclean/cpp/src/cleaner.cpp
vecclean/dedup/chunk_dedup.py
vecclean/dedup/sentence_dedup.py
vecclean/ingest/detect.py
vecclean/utils/hashing.py
vecclean/utils/io.py
vecclean/utils/logging.py
vecclean/utils/timing.py
vecclean-1.0.0.post3.dist-info/licenses/LICENSE
vecclean-1.0.0.post3.dist-info/METADATA
vecclean-1.0.0.post3.dist-info/WHEEL
vecclean-1.0.0.post3.dist-info/entry_points.txt
vecclean-1.0.0.post3.dist-info/top_level.txt
vecclean-1.0.0.post3.dist-info/RECORD
