Metadata-Version: 2.4
Name: vecclean
Version: 1.0.0.post3
Summary: Production-ready text cleaning, deduplication, and vectorization pipeline with C++ acceleration
Author-email: Shlok Mundhra <shlokmundhra1111@gmail.com>
License: MIT
Project-URL: Homepage, https://github.com/vecclean/vecclean
Project-URL: Documentation, https://vecclean.readthedocs.io
Project-URL: Repository, https://github.com/vecclean/vecclean
Project-URL: Issues, https://github.com/vecclean/vecclean/issues
Project-URL: Changelog, https://github.com/vecclean/vecclean/blob/main/CHANGELOG.md
Keywords: text-processing,vectorization,deduplication,nlp,embeddings,fastapi
Classifier: Development Status :: 5 - Production/Stable
Classifier: Intended Audience :: Developers
Classifier: Intended Audience :: Science/Research
Classifier: License :: OSI Approved :: MIT License
Classifier: Programming Language :: Python :: 3
Classifier: Programming Language :: Python :: 3.9
Classifier: Programming Language :: Python :: 3.10
Classifier: Programming Language :: Python :: 3.11
Classifier: Programming Language :: Python :: 3.12
Classifier: Programming Language :: C++
Classifier: Topic :: Scientific/Engineering :: Artificial Intelligence
Classifier: Topic :: Text Processing :: Linguistic
Classifier: Topic :: Software Development :: Libraries :: Python Modules
Requires-Python: >=3.9
License-File: LICENSE
Requires-Dist: fastapi>=0.104.0
Requires-Dist: uvicorn[standard]>=0.24.0
Requires-Dist: pydantic>=2.4.0
Requires-Dist: pydantic-settings>=2.0.0
Requires-Dist: click>=8.1.0
Requires-Dist: rich>=13.6.0
Requires-Dist: typer>=0.9.0
Requires-Dist: httpx>=0.25.0
Requires-Dist: zstandard>=0.21.0
Requires-Dist: aiofiles>=23.2.0
Requires-Dist: asyncio-throttle>=1.0.2
Requires-Dist: sentence-transformers>=2.2.0
Requires-Dist: transformers>=4.30.0
Requires-Dist: torch!=2.2.0,>=2.0.0
Requires-Dist: numpy<2.0.0,>=1.22.0
Requires-Dist: PyPDF2>=3.0.0
Requires-Dist: pdfplumber>=0.9.0
Requires-Dist: python-docx>=0.8.11
Requires-Dist: python-pptx>=0.6.21
Requires-Dist: beautifulsoup4>=4.12.0
Requires-Dist: lxml>=4.9.0
Requires-Dist: tiktoken>=0.5.0
Requires-Dist: transformers>=4.30.0
Requires-Dist: aiosqlite>=0.19.0
Requires-Dist: asyncpg>=0.28.0
Requires-Dist: aioredis>=2.0.0
Requires-Dist: PyJWT>=2.8.0
Requires-Dist: python-multipart>=0.0.6
Requires-Dist: pandas>=2.1.0
Requires-Dist: pyarrow>=13.0.0
Requires-Dist: xxhash>=3.4.0
Requires-Dist: PyYAML>=6.0.1
Requires-Dist: watchdog>=3.0.0
Requires-Dist: psutil>=5.9.0
Requires-Dist: lz4>=4.3.0
Requires-Dist: zstandard>=0.21.0
Requires-Dist: brotli>=1.1.0
Requires-Dist: aioboto3>=12.0.0; extra == "aws"
Requires-Dist: google-cloud-storage>=2.10.0; extra == "gcp"
Requires-Dist: azure-storage-blob>=12.19.0; extra == "azure"
Requires-Dist: azure-identity>=1.15.0; extra == "azure"
Provides-Extra: aws
Requires-Dist: aioboto3>=12.0.0; extra == "aws"
Provides-Extra: gcp
Requires-Dist: google-cloud-storage>=2.10.0; extra == "gcp"
Provides-Extra: azure
Requires-Dist: azure-storage-blob>=12.19.0; extra == "azure"
Requires-Dist: azure-identity>=1.15.0; extra == "azure"
Provides-Extra: cloud
Requires-Dist: aioboto3>=12.0.0; extra == "cloud"
Requires-Dist: google-cloud-storage>=2.10.0; extra == "cloud"
Requires-Dist: azure-storage-blob>=12.19.0; extra == "cloud"
Requires-Dist: azure-identity>=1.15.0; extra == "cloud"
Provides-Extra: dev
Requires-Dist: pytest>=7.4.0; extra == "dev"
Requires-Dist: pytest-asyncio>=0.21.0; extra == "dev"
Requires-Dist: pytest-benchmark>=4.0.0; extra == "dev"
Requires-Dist: pytest-cov>=4.1.0; extra == "dev"
Requires-Dist: black>=23.9.0; extra == "dev"
Requires-Dist: ruff>=0.1.0; extra == "dev"
Requires-Dist: mypy>=1.6.0; extra == "dev"
Requires-Dist: pre-commit>=3.5.0; extra == "dev"
Requires-Dist: sphinx>=7.1.0; extra == "dev"
Requires-Dist: sphinx-rtd-theme>=1.3.0; extra == "dev"
Provides-Extra: all
Requires-Dist: aioboto3>=12.0.0; extra == "all"
Requires-Dist: google-cloud-storage>=2.10.0; extra == "all"
Requires-Dist: azure-storage-blob>=12.19.0; extra == "all"
Requires-Dist: azure-identity>=1.15.0; extra == "all"
Requires-Dist: pytest>=7.4.0; extra == "all"
Requires-Dist: pytest-asyncio>=0.21.0; extra == "all"
Requires-Dist: pytest-benchmark>=4.0.0; extra == "all"
Requires-Dist: pytest-cov>=4.1.0; extra == "all"
Requires-Dist: black>=23.9.0; extra == "all"
Requires-Dist: ruff>=0.1.0; extra == "all"
Requires-Dist: mypy>=1.6.0; extra == "all"
Requires-Dist: pre-commit>=3.5.0; extra == "all"
Dynamic: license-file
